beetsplug/goingrunning/__init__.py
beetsplug/goingrunning/about.py
beetsplug/goingrunning/command.py
beetsplug/goingrunning/common.py
beetsplug/goingrunning/config_default.yml
beetsplug/goingrunning/itemexport.py
beetsplug/goingrunning/itemorder.py
beetsplug/goingrunning/itempick.py
beets_goingrunning-1.2.10.dist-info/LICENSE.txt
beets_goingrunning-1.2.10.dist-info/METADATA
beets_goingrunning-1.2.10.dist-info/WHEEL
beets_goingrunning-1.2.10.dist-info/top_level.txt
beets_goingrunning-1.2.10.dist-info/RECORD
