Metadata-Version: 2.1
Name: beets-goingrunning
Version: 1.2.10
Summary: ('A beets plugin for creating and exporting songs that match your running session.',)
Home-page: https://github.com/adamjakab/BeetsPluginGoingRunning
Author: Adam Jakab
Author-email: adam@jakab.pro
License: MIT
Platform: ALL
Classifier: Topic :: Multimedia :: Sound/Audio
Classifier: License :: OSI Approved :: MIT License
Classifier: Environment :: Console
Classifier: Programming Language :: Python :: 3
Classifier: Programming Language :: Python :: 3.8
Classifier: Programming Language :: Python :: 3.9
Classifier: Programming Language :: Python :: 3.10
Classifier: Programming Language :: Python :: 3.11
Classifier: Programming Language :: Python :: 3.12
Requires-Python: >=3.8
License-File: LICENSE.txt
Requires-Dist: beets >=1.4.9
Requires-Dist: alive-progress
Provides-Extra: tests
Requires-Dist: requests ; extra == 'tests'
